secretshare/__init__.py
secretshare/calc.py
secretshare/primes.py
secretshare/secretshare.py
secretshare-0.6.0.dist-info/LICENSE
secretshare-0.6.0.dist-info/METADATA
secretshare-0.6.0.dist-info/WHEEL
secretshare-0.6.0.dist-info/top_level.txt
secretshare-0.6.0.dist-info/RECORD
