Metadata-Version: 2.1
Name: secretshare
Version: 0.6.0
Summary: Share a secret securely implementing Shamir's secret share
Home-page: http://github.com/hackancuba/secretshare-py
Author: HacKan
Author-email: hackan@gmail.com
License: GPLv3+
Download-URL: https://github.com/HacKanCuBa/secretshare-py/releases
Keywords: cryptography shamir secret share security
Platform: POSIX :: Linux
Classifier: Development Status :: 4 - Beta
Classifier: Environment :: Other Environment
Classifier: Intended Audience :: Developers
Classifier: License :: OSI Approved :: GNU General Public License v3 or later (GPLv3+)
Classifier: Natural Language :: English
Classifier: Operating System :: POSIX :: Linux
Classifier: Programming Language :: Python :: 3
Classifier: Programming Language :: Python :: 3.6
Classifier: Programming Language :: Python :: 3.7
Classifier: Topic :: Security :: Cryptography
Classifier: Topic :: Utilities
Classifier: Typing :: Typed
Requires-Python: >=3.6
Requires-Dist: hc-passphrase
